derrom/__init__.py
derrom/dim_reducers.py
derrom/estimator.py
derrom/optimizers.py
derrom/scalers.py
derrom/transformers.py
derrom/utils.py
derrom-1.0.dist-info/WHEEL
derrom-1.0.dist-info/METADATA
derrom-1.0.dist-info/RECORD
