Metadata-Version: 2.1
Name: derrom
Version: 1.0
Summary: Derrom is a delay embedded regressive reduced order model 
Author-email: Stefan Meinecke <stefan.meinecke@posteo.de>, Felix Köster <Felix-Koester@hotmail.com>
Requires-Python: >=3.7
Classifier: Programming Language :: Python :: 3
Classifier: Programming Language :: Python :: 3.9
Classifier: Operating System :: OS Independent
Classifier: Intended Audience :: Science/Research
Classifier: License :: OSI Approved :: MIT License
Classifier: Topic :: Scientific/Engineering :: Mathematics
Project-URL: Homepage, https://github.com/stmeinecke/derrom
